robohive_init.py
robohive/__init__.py
robohive/__pycache__/__init__.cpython-310.pyc
robohive/__pycache__/__init__.cpython-39.pyc
robohive/envs/__init__.py
robohive/envs/env_base.py
robohive/envs/env_variants.py
robohive/envs/obs_vec_dict.py
robohive/envs/__pycache__/__init__.cpython-39.pyc
robohive/envs/__pycache__/env_base.cpython-39.pyc
robohive/envs/__pycache__/env_variants.cpython-39.pyc
robohive/envs/__pycache__/obs_vec_dict.cpython-39.pyc
robohive/envs/arms/__init__.py
robohive/envs/arms/pick_place_v0.py
robohive/envs/arms/push_base_v0.py
robohive/envs/arms/reach_base_v0.py
robohive/envs/arms/__pycache__/__init__.cpython-39.pyc
robohive/envs/arms/__pycache__/pick_place_v0.cpython-39.pyc
robohive/envs/arms/__pycache__/push_base_v0.cpython-39.pyc
robohive/envs/arms/__pycache__/reach_base_v0.cpython-39.pyc
robohive/envs/arms/fetch/assets/fetch_reach_v0.config
robohive/envs/arms/fetch/assets/fetch_reach_v0.xml
robohive/envs/arms/franka/assets/franka_busbin_v0.config
robohive/envs/arms/franka/assets/franka_busbin_v0.xml
robohive/envs/arms/franka/assets/franka_reach_v0.config
robohive/envs/arms/franka/assets/franka_reach_v0.xml
robohive/envs/arms/franka/assets/franka_ycb_v0.config
robohive/envs/arms/franka/assets/franka_ycb_v0.xml
robohive/envs/claws/__init__.py
robohive/envs/claws/reorient_v0.py
robohive/envs/claws/__pycache__/__init__.cpython-39.pyc
robohive/envs/claws/__pycache__/reorient_v0.cpython-39.pyc
robohive/envs/claws/trifinger/trifinger_reorient.xml
robohive/envs/fm/__init__.py
robohive/envs/fm/franka_ee_pose_v0.py
robohive/envs/fm/franka_robotiq_data_v0.py
robohive/envs/fm/__pycache__/__init__.cpython-39.pyc
robohive/envs/fm/__pycache__/franka_ee_pose_v0.cpython-39.pyc
robohive/envs/fm/__pycache__/franka_robotiq_data_v0.cpython-39.pyc
robohive/envs/fm/assets/dmanus.config
robohive/envs/fm/assets/dmanus.xml
robohive/envs/fm/assets/franka_dmanus.config
robohive/envs/fm/assets/franka_dmanus.xml
robohive/envs/fm/assets/franka_robotiq.config
robohive-0.7.0.dist-info/LICENSE
robohive-0.7.0.dist-info/METADATA
robohive-0.7.0.dist-info/WHEEL
robohive-0.7.0.dist-info/entry_points.txt
robohive-0.7.0.dist-info/top_level.txt
robohive-0.7.0.dist-info/RECORD
