Metadata-Version: 2.1
Name: robohive
Version: 0.7.0
Summary: A Unified Framework for Robot Learning
Home-page: https://github.com/vikashplus/robohive.git
Author: Vikash Kumar
Author-email: vikahsplus@gmail.com
License: Apache 2.0
License-File: LICENSE
Requires-Dist: click
Requires-Dist: gymnasium (==0.29.1)
Requires-Dist: mujoco (==3.1.3)
Requires-Dist: dm-control (==1.0.16)
Requires-Dist: termcolor
Requires-Dist: sk-video
Requires-Dist: flatten-dict
Requires-Dist: matplotlib
Requires-Dist: ffmpeg
Requires-Dist: absl-py
Requires-Dist: torch
Requires-Dist: h5py (==3.7.0)
Requires-Dist: pink-noise-rl
Requires-Dist: gitpython
Provides-Extra: a0
Requires-Dist: pycapnp (>=1.1.1) ; extra == 'a0'
Requires-Dist: alephzero ; extra == 'a0'
Provides-Extra: encoder
Requires-Dist: torchvision ; extra == 'encoder'
Provides-Extra: mujoco_py
Requires-Dist: free-mujoco-py ; extra == 'mujoco_py'
